{
  "no": "R26BK01631069",
  "name": "안동시 도시재생 전략계획 및 활성화 수립 용역(협상)",
  "org": "경상북도 안동시 (건축과)",
  "amt": "3.09억 (VAT 포함)",
  "dday": "확인 필요 (공고 메타 clse 값 없음 — 원문 공고서에서 제안서 접수 마감일시 확인)",
  "gen": "생성 2026-07-18",
  "overview": [
    ["발주처", "경상북도 안동시 건축과 (담당 금보경 · 054-840-6136)"],
    ["예산", "309,290,000원 VAT 포함 / 추정가격 281,172,727원 (VAT 별도)"],
    ["계약방식", "제한경쟁입찰 · 협상에 의한 계약 (지계령 제43조)"],
    ["과업기간", "착수일로부터 540일 (18개월)"],
    ["대상범위", "공간: 안동시 도시지역 일원 / 시간: 기준 2026년~목표 2036년"],
    ["과업성격", "도시재생 전략계획 수립(정비) + 활성화계획 수립 + 국토부 공모제안서 작성"],
    ["참가자격", "학술연구용역(업종코드 1169) 등록 + 조달청 입찰참가자격 등록업체 (면허보완 공동도급 가능)"]
  ],
  "summary": "「도시재생 활성화 및 지원에 관한 특별법」 제12·13조에 근거해 안동시 도시재생 전략계획을 전면 재수립(정비)하고, 활성화지역 지정·활성화계획 수립·국토부 공모제안서 작성까지 수행하는 법정계획 수립 용역이다. 핵심 과업은 기초조사·쇠퇴진단(집계구/행정동 단위 복합쇠퇴지수)·활성화지역 지정·재원조달계획·추진체계·성과관리로, 도시계획 엔지니어링/학술연구기관 영역에 정확히 속한다. 공간연출·전시·실감콘텐츠 요소는 사실상 없으며, 참여기술자도 도시계획·건축·주거환경 기술사/박사 중심을 요구한다.",
  "scope": [
    "2036 도시재생 전략계획 수립(정비): 기초조사(인문사회·산업경제·물리환경)·쇠퇴진단·비전/목표·재생권역 설정",
    "도시재생활성화지역 지정·변경 (복합쇠퇴지수·주거취약지수, 혁신지구·지역특화재생 유형 구분)",
    "활성화지역별 우선순위·연계방안 및 재원조달·예산집행계획(국·도비/지방비/민간투자) 수립",
    "추진체계·도시재생지원센터 운영방안, 성과관리(모니터링)·평가지표 설정",
    "도시재생 활성화계획(00지구) 수립 및 국토교통부 공모제안서 작성",
    "주민공청회·지방의회 의견청취·지방도시재생위원회 심의 등 법정 행정절차 이행 (전문자문단 5인+·현장참여단 10인+ 운영)"
  ],
  "scoring": {
    "rows": [
      {"group": "정량(20)", "item": "기술인력 보유상태 — 사업총괄/분야별 책임기술자(도시계획) 자격·경력, 기술사·박사~초급 등급 절대평가", "pt": "6"},
      {"group": "정량(20)", "item": "수행경험(실적) — 최근 5년 준공한 '도시재생 전략계획/활성화계획 수립·변경' 유사실적. 건수 3.0(4건미만~10건+) + 금액 3.0(4억미만~10억+)", "pt": "6", "key": true},
      {"group": "정량(20)", "item": "신인도 — 입찰참가제한·업무정지 감점 (절대평가)", "pt": "4"},
      {"group": "정량(20)", "item": "경영상태 — 신용평가등급확인서 (AAA 4.0 ~ 미제출 0)", "pt": "4"},
      {"group": "정성(60)", "item": "과업의 이해 및 도시재생전략계획 목표제시 — 총괄책임자·업체 전문성, 상위/관련계획·법규 반영, 지역자원조사", "pt": "10"},
      {"group": "정성(60)", "item": "과업수행 추진체계 및 맞춤형 도시재생 추진방향 — 계획수립 방향, 조직구성·업무분장, 지역여건 진단", "pt": "10"},
      {"group": "정성(60)", "item": "목표달성을 위한 창의적 실현방안 제시 — 사업목표 합리성, 시행방안 독창성, 전략계획 변경전략·기본구상", "pt": "10", "key": true},
      {"group": "정성(60)", "item": "제안내용의 적절성 — 사업내용 구체성, 실천방안·단계별 목표 적절성 (지역특성 반영 수행방안)", "pt": "10"},
      {"group": "정성(60)", "item": "기술활용 및 경제성 — 지역자원·특성 반영 특성화, 주민역량강화·공동체 활성화, 지역경제·일자리 파급효과", "pt": "10", "key": true},
      {"group": "정성(60)", "item": "지역발전 및 지속가능성 — 지역 기여도, 사후관리 시스템, 지속가능성 평가·모니터링 계획", "pt": "10"},
      {"group": "가격(20)", "item": "입찰가격 평가 (배점비율 20%, 예규 제344호 산식)", "pt": "20"}
    ],
    "note": "★ 기술능력 80(정량20+정성60) + 가격20, 협상적격 커트라인 70점. 정성 60점은 6개 항목 균등 10점 배분이며 전부 '도시재생 계획수립' 역량(쇠퇴진단·활성화지역 지정·재원조달·성과관리) 평가라 공간연출·전시·경관 강점을 투영할 자리가 사실상 없다. 실질 승부는 정량 실적(도시재생 전략/활성화계획 준공실적)과 도시계획 기술사·박사 인력에서 갈리며, 이 두 정량 항목이 우리 팀 기준으로 가장 취약한 게이트키퍼다."
  },
  "qualification": [
    "조달청 입찰참가자격 등록업체이며 학술연구용역(업종코드 1169)를 입찰서 제출마감일 전일까지 등록한 업체",
    "지계령 제13조·시행규칙 제14조 참가자격 충족 및 제92조 부정당업자 제한 비해당",
    "정량 실적(6점): 최근 5년간 국가·지자체·공공기관 발주 '준공한' 도시재생 전략계획/활성화계획 수립·변경 등 유사용역 — 건수(10건+ 만점)·금액(10억+ 만점), 4건·4억 미만이면 최저점. 실적증명서(발주처/엔지니어링협회) 제출분만 인정, 유사성은 발주처가 판정",
    "기술인력: 도시계획 등 분야 사업총괄/분야별 책임기술자 자격·경력(기술사/박사~초급, 엔지니어링산업진흥법 등급 기준)",
    "면허 보완을 위한 공동도급 가능 (대표사는 지분비율 최고, 실적건수 지분무관 1건·금액은 지분 적용)"
  ],
  "fit": {
    "verdict": "보류",
    "reasons": [
      "과업 본질이 「도시재생법」 제12·13조 법정 '전략계획 수립(정비)' — 쇠퇴진단·활성화지역 지정·재원조달·추진체계·성과관리로, 도시계획 엔지니어링사/학술연구기관의 정통 영역이며 시그마애드(호진팀)의 공공디자인·전시·공간연출·경관 정체성과 본질적으로 다르다",
      "정성 60점 6개 항목이 전부 계획수립 역량 평가라 우리의 '보여주는 싸움'(도면·조감도·연출 시나리오) 강점을 투영할 배점 구간이 없다 — 태종대 서비스디자인·부산디자인클러스터형 승부처가 부재",
      "정량 실적요건이 '도시재생 전략/활성화계획 준공실적'으로 특정되어 있어 전시·공간연출 실적으로는 대체 불가. 도시계획 기술사·박사 인력 요구까지 겹쳐 단독 참여 자체가 어렵다"
    ],
    "risks": [
      "실적요건 대응은 도시계획 엔지니어링사와의 공동도급(면허보완)이 사실상 전제 — 이 경우 우리 역할은 경관·공공디자인·주민참여 '보조 지분'에 그쳐 주력 수주로서 실익이 낮다",
      "제안서 접수 마감일시가 메타(clse)에 비어 있어 원문 공고서에서 반드시 확인 필요 — 방문제출(우편 불가), 안동시 건축과 제출",
      "가격배점 20% + 협상계약 구조상 기술 80점이 관건이나, 그 80점의 대부분이 우리가 열위인 도시계획 실적·인력·계획역량이라 진입해도 승산이 구조적으로 낮다"
    ]
  },
  "schedule": [
    ["제안서 접수 마감", "공고서 참조 (확인 필요) · 방문제출, 접수 시 평가위원 추첨"],
    ["제안서 평가", "접수 후 별도 안내"],
    ["우선협상대상자 선정·통보", "선정 후 개별통보"],
    ["과업기간", "착수일로부터 540일(18개월)"]
  ],
  "source": "나라장터 API 자동수집→제안요청서 자동추출→배점 역산 분석. 공고번호 R26BK01631069. 최종 판단 전 원문 대조 권장."
}
